s3splitmerge/__init__.py
s3splitmerge/_version.py
s3splitmerge/cli.py
s3splitmerge/exc.py
s3splitmerge/helpers.py
s3splitmerge/merge.py
s3splitmerge/options.py
s3splitmerge/split.py
s3splitmerge/__pycache__/__init__.cpython-38.pyc
s3splitmerge/__pycache__/_version.cpython-38.pyc
s3splitmerge/__pycache__/exc.cpython-38.pyc
s3splitmerge/__pycache__/helpers.cpython-38.pyc
s3splitmerge/__pycache__/merge.cpython-38.pyc
s3splitmerge/__pycache__/options.cpython-38.pyc
s3splitmerge/__pycache__/split.cpython-38.pyc
s3splitmerge/docs/__init__.py
s3splitmerge/tests/__init__.py
s3splitmerge/tests/aws.py
s3splitmerge/tests/data.py
s3splitmerge/tests/run.py
s3splitmerge/tests/__pycache__/__init__.cpython-38.pyc
s3splitmerge/tests/__pycache__/aws.cpython-38.pyc
s3splitmerge/tests/__pycache__/data.cpython-38.pyc
s3splitmerge/tests/__pycache__/run.cpython-38.pyc
s3splitmerge-0.0.1.dist-info/AUTHORS.rst
s3splitmerge-0.0.1.dist-info/LICENSE.txt
s3splitmerge-0.0.1.dist-info/METADATA
s3splitmerge-0.0.1.dist-info/WHEEL
s3splitmerge-0.0.1.dist-info/entry_points.txt
s3splitmerge-0.0.1.dist-info/top_level.txt
s3splitmerge-0.0.1.dist-info/RECORD
