Metadata-Version: 2.1
Name: s3splitmerge
Version: 0.0.1
Summary: Package short description.
Home-page: https://github.com/MacHu-GWU/
Author: Sanhe Hu
Author-email: husanhe@gmail.com
Maintainer: Unknown
License: MIT
Download-URL: https://pypi.python.org/pypi/s3splitmerge/0.0.1#downloads
Platform: Windows
Platform: MacOS
Platform: Unix
Classifier: Development Status :: 4 - Beta
Classifier: Intended Audience :: Developers
Classifier: License :: OSI Approved :: MIT License
Classifier: Natural Language :: English
Classifier: Operating System :: Microsoft :: Windows
Classifier: Operating System :: MacOS
Classifier: Operating System :: Unix
Classifier: Programming Language :: Python
Classifier: Programming Language :: Python :: 2.7
Classifier: Programming Language :: Python :: 3.4
Classifier: Programming Language :: Python :: 3.5
Classifier: Programming Language :: Python :: 3.6
License-File: LICENSE.txt
License-File: AUTHORS.rst
Requires-Dist: smart-open
Provides-Extra: docs
Requires-Dist: sphinx (==3.5.4) ; extra == 'docs'
Requires-Dist: furo (==2021.6.18b36) ; extra == 'docs'
Requires-Dist: sphinx-inline-tabs (==2021.3.28b7) ; extra == 'docs'
Requires-Dist: sphinx-jinja (==1.1.0) ; extra == 'docs'
Requires-Dist: sphinx-copybutton (==0.2.5) ; extra == 'docs'
Requires-Dist: docfly (==0.0.18) ; extra == 'docs'
Requires-Dist: rstobj (==0.0.7) ; extra == 'docs'
Requires-Dist: pygments ; extra == 'docs'
Provides-Extra: tests
Requires-Dist: pytest ; extra == 'tests'
Requires-Dist: pytest-cov ; extra == 'tests'
Requires-Dist: pathlib-mate ; extra == 'tests'
